azureml/__init__.py
azureml/contrib/__init__.py
azureml/contrib/gbdt/__init__.py
azureml/contrib/gbdt/lightgbm.py
azureml/contrib/gbdt/run_lgbm.py
azureml_contrib_gbdt-1.29.0.dist-info/DESCRIPTION.rst
azureml_contrib_gbdt-1.29.0.dist-info/LICENSE.txt
azureml_contrib_gbdt-1.29.0.dist-info/METADATA
azureml_contrib_gbdt-1.29.0.dist-info/RECORD
azureml_contrib_gbdt-1.29.0.dist-info/WHEEL
azureml_contrib_gbdt-1.29.0.dist-info/metadata.json
azureml_contrib_gbdt-1.29.0.dist-info/top_level.txt
