Metadata-Version: 2.0
Name: azureml-contrib-gbdt
Version: 1.29.0
Summary: azureml contrit gradient boosted decision tree
Home-page: https://docs.microsoft.com/python/api/overview/azure/ml/?view=azure-ml-py
Author: Microsoft Corp
Author-email: azpycli@microsoft.com
License: Proprietary https://aka.ms/azureml-preview-sdk-license 
Platform: UNKNOWN
Classifier: Development Status :: 3 - Alpha
Classifier: Intended Audience :: Developers
Classifier: Intended Audience :: Science/Research
Classifier: License :: Other/Proprietary License
Classifier: Programming Language :: Python :: 3
Classifier: Programming Language :: Python :: 3.6
Classifier: Topic :: Scientific/Engineering :: Artificial Intelligence
Classifier: Operating System :: Microsoft :: Windows
Classifier: Operating System :: MacOS
Classifier: Operating System :: POSIX :: Linux
Requires-Python: >=3.6,<4
Requires-Dist: azureml-core (~=1.29.0)
Requires-Dist: azureml-train-core (~=1.29.0)
